{
  "config": {
    "title": "Header",
    "description": "My awesome app using docz",
    "menu": [],
    "ordering": "descending",
    "version": "0.0.0-development",
    "repository": "https://github.com/debtcollective/header",
    "native": false,
    "codeSandbox": true,
    "themeConfig": {}
  },
  "entries": {
    "src/appbar/AppBar.mdx": {
      "name": "AppBar",
      "id": "02bfa1e49d50ff504b7f92214fe58af1",
      "filepath": "src/appbar/AppBar.mdx",
      "link": "https://github.com/debtcollective/header/edit/master/src/appbar/AppBar.mdx",
      "slug": "src-appbar-app-bar",
      "route": "/src-appbar-app-bar",
      "order": 0,
      "menu": null,
      "headings": [
        {
          "depth": 1,
          "slug": "appbar",
          "value": "AppBar"
        },
        {
          "depth": 2,
          "slug": "basic-usage",
          "value": "Basic usage"
        }
      ]
    },
    "src/menu/Menu.mdx": {
      "name": "Menu",
      "id": "b2e7162645a8081ff5a64b9470c3f879",
      "filepath": "src/menu/Menu.mdx",
      "link": "https://github.com/debtcollective/header/edit/master/src/menu/Menu.mdx",
      "slug": "src-menu-menu",
      "route": "/src-menu-menu",
      "order": 0,
      "menu": null,
      "headings": [
        {
          "depth": 1,
          "slug": "menu",
          "value": "Menu"
        },
        {
          "depth": 2,
          "slug": "basic-usage",
          "value": "Basic usage"
        },
        {
          "depth": 2,
          "slug": "types",
          "value": "Types"
        }
      ]
    },
    "src/session/Session.mdx": {
      "name": "Session",
      "id": "93a92784a988244564ad2ec2d2269a13",
      "filepath": "src/session/Session.mdx",
      "link": "https://github.com/debtcollective/header/edit/master/src/session/Session.mdx",
      "slug": "src-session-session",
      "route": "/src-session-session",
      "order": 0,
      "menu": null,
      "headings": [
        {
          "depth": 1,
          "slug": "session",
          "value": "Session"
        },
        {
          "depth": 2,
          "slug": "render-user-props",
          "value": "Render User props"
        },
        {
          "depth": 2,
          "slug": "render-actions",
          "value": "Render Actions"
        },
        {
          "depth": 2,
          "slug": "types",
          "value": "Types"
        }
      ]
    },
    "src/profile/Profile.mdx": {
      "name": "Profile",
      "id": "ca512db99ad435a262a1eea694f74cc6",
      "filepath": "src/profile/Profile.mdx",
      "link": "https://github.com/debtcollective/header/edit/master/src/profile/Profile.mdx",
      "slug": "src-profile-profile",
      "route": "/src-profile-profile",
      "order": 0,
      "menu": null,
      "headings": [
        {
          "depth": 1,
          "slug": "profile",
          "value": "Profile"
        },
        {
          "depth": 2,
          "slug": "alertsdropdown",
          "value": "AlertsDropdown"
        },
        {
          "depth": 2,
          "slug": "inboxdropdown",
          "value": "InboxDropdown"
        },
        {
          "depth": 2,
          "slug": "useravatardropdown",
          "value": "UserAvatarDropdown"
        },
        {
          "depth": 2,
          "slug": "profileitems",
          "value": "ProfileItems"
        },
        {
          "depth": 2,
          "slug": "basic-usage",
          "value": "Basic usage"
        },
        {
          "depth": 2,
          "slug": "types",
          "value": "Types"
        }
      ]
    }
  }
}
